{
  "updated": "2026-07-21T04:56:33.971Z",
  "source": "https://www.parentmap.com/things-to-do/the-weekender/",
  "events": [
    {
      "n": 1,
      "title": "Take a Spin at LeMay",
      "date": "Friday, July 17",
      "cost": "Included with admission ($17.50–$24.50) or membership",
      "costType": "paid",
      "region": "South Sound",
      "loc": "LeMay – America’s Car Museum , 2702 E. D St., Tacoma",
      "lat": 47.2357021,
      "lng": -122.4303289,
      "approx": false,
      "url": "https://www.parentmap.com/calendar/take-a-spin-at-lemay",
      "desc": "If you’ve ever visited LeMay, you’ve likely daydreamed about taking a spin in one of the cars from the museum’s collections. That dream can become a reality this weekend, with a spin around Haub Family Field. Make a day of it wandering the museum exhibits, and plan for lunch at the new café."
    },
    {
      "n": 2,
      "title": "Fircrest Fun Days",
      "date": "Friday–Saturday, July 17–18",
      "cost": "Free",
      "costType": "free",
      "region": "South Sound",
      "loc": "Fircrest Park , 555 Contra Costa Ave., Fircrest",
      "lat": 47.2338927,
      "lng": -122.5127218,
      "approx": false,
      "url": "https://www.parentmap.com/series/46697-series-415985",
      "desc": "Travel back in time this weekend to the Old West with this themed festival. There will be live concerts, artist and vendor booths, plenty of food trucks, and a couple of bake-offs. You can also expect story time, face painting and interactive activities in the Kidz Zone. Plus, there will be fireworks on Saturday!"
    },
    {
      "n": 3,
      "title": "GeekFest West",
      "date": "Friday–Sunday, July 17–19",
      "cost": "$5–$35",
      "costType": "paid",
      "region": "North Sound",
      "loc": "Lynnwood Event Center , 3711 196th St., Lynnwood",
      "lat": 47.8213778,
      "lng": -122.2834694,
      "approx": false,
      "url": "https://www.parentmap.com/series/geekfest-west-series-425492",
      "desc": "Considered the largest geek event in Snohomish County, GeekFest West has something for everyone. There will be indoor and outdoor entertainment ranging from cosplay and LARPing to chess, video games and pinball. Sunday’s events are especially geared toward families, with children’s cosplay demos, video game and arcade tournaments, tutorials and more."
    },
    {
      "n": 4,
      "title": "Kla Ha Ya Days",
      "date": "Friday–Sunday, July 17–19",
      "cost": "Free",
      "costType": "free",
      "region": "North Sound",
      "loc": "Historic Downtown Snohomish , 1024 First St., Snohomish",
      "lat": 47.9115981,
      "lng": -122.095657,
      "approx": false,
      "url": "https://www.parentmap.com/series/kla-ha-ya-days-series-422043",
      "desc": "I always love spending a day in downtown Snohomish — from a perfect brunch to excellent shopping — but it really comes to life during this annual summer fest. Kla Ha Ya Days is a longstanding tradition with over 100 years of history. Friday will have a special kids fair and outdoor movie, while Saturday brings a pancake breakfast, street fair, parade and circus performances. Don’t miss the car …"
    },
    {
      "n": 5,
      "title": "Family Fun Day at Highline SeaTac Botanical Garden",
      "date": "Saturday, July 18",
      "cost": "Free",
      "costType": "free",
      "region": "Seattle Area",
      "loc": "Highline SeaTac Botanical Garden , 13735 24th Ave. S., SeaTac",
      "lat": 47.4795849,
      "lng": -122.3037382,
      "approx": false,
      "url": "https://www.parentmap.com/calendar/family-fun-day-highline-seatac-botanical-garden",
      "desc": "What kid wouldn’t be amazed by seeing someone walk by on stilts? This garden fest will not only have stilt walking, but also live music and more entertainment for families. Try out yoga in the garden, watch special demonstrations, and learn about pollinators and their favorite plants."
    },
    {
      "n": 6,
      "title": "Lavender Festival",
      "date": "Saturday–Sunday, July 18–19",
      "cost": "$9",
      "costType": "paid",
      "region": "Eastside",
      "loc": "JB Family Growers , 14063 N.E. 145th St., Woodinville",
      "lat": 47.7325957,
      "lng": -122.1494897,
      "approx": false,
      "url": "https://www.parentmap.com/series/lavender-festival",
      "desc": "I look forward to lavender being in bloom every summer! While I’d love to make the trek out to Sequim , this lavender festival on the Eastside is closer to home and just as delightful. Fields filled with 15,000 lavender plants are in full bloom (and sunflowers are starting to show their faces, too). Sip on lavender lemonade, walk the fields and shop from local vendors."
    },
    {
      "n": 7,
      "title": "SandBlast Festival of the Arts",
      "date": "Saturday–Sunday, July 18–19",
      "cost": "Free",
      "costType": "free",
      "region": "Eastside",
      "loc": "McCormick Park , 26200 N.E. Stephens St., Duvall",
      "lat": 47.7398874,
      "lng": -121.9901084,
      "approx": false,
      "url": "https://www.parentmap.com/series/26433-series-410876",
      "desc": "Artists carve incredible sculptures from sand on the beach at this two-day festival. I am in awe of what they have created at past events (maybe because my family has only ever been able to build lopsided sand castles on the beach). Get inspired by the sand carvers at work, admire local artwork and enjoy the live music."
    },
    {
      "n": 8,
      "title": "Downtown Seattle Block Party",
      "date": "Saturday–Sunday, July 18–19",
      "cost": "Free",
      "costType": "free",
      "region": "Seattle Area",
      "loc": "Westlake Park , 401 Pine St., Seattle",
      "lat": 47.6109571,
      "lng": -122.3370147,
      "approx": false,
      "url": "https://www.parentmap.com/series/downtown-seattle-block-party-2",
      "desc": "It’s no secret that I love a shopping day, and the Nordstrom Anniversary Sale is coming up. It all kicks off with this downtown block party, complete with kid-friendly activities, games, live entertainment and more. The Mariner Moose and Blitz the Seahawk will be making appearances, too!"
    },
    {
      "n": 9,
      "title": "Seattle Bon Odori Festival",
      "date": "Saturday–Sunday, July 18–19",
      "cost": "Free",
      "costType": "free",
      "region": "Seattle Area",
      "loc": "Seattle Betsuin Buddhist Temple , 1427 S. Main St., Seattle",
      "lat": 47.5997302,
      "lng": -122.3132184,
      "approx": false,
      "url": "https://www.parentmap.com/series/seattle-bon-odori-festival",
      "desc": "Thrilling taiko drumming performances, Japanese folk dancing and more festivities await at this incredible summer celebration honoring ancestral spirits. While you’re there, you can try delicious foods (I can never resist shaved ice) and shop the delightful thrift store. Grown-ups can plan for a pit stop at the beer garden — don’t miss the lively tunes from local reggae band Two Story Zori."
    },
    {
      "n": 10,
      "title": "Parade of Nations and Watch Party",
      "date": "Sunday, July 19",
      "cost": "Free",
      "costType": "free",
      "region": "Seattle Area",
      "loc": "Rainier Playfields , 3700 S. Alaska St., Seattle",
      "lat": 47.561706,
      "lng": -122.286303,
      "approx": false,
      "url": "https://www.parentmap.com/calendar/parade-of-nations-and-watch-party",
      "desc": "The thrilling World Cup comes to an end this weekend with a final match at noon on Sunday. Celebrate beforehand with a parade that highlights diversity and unity across cultures. There will also be soccer-themed activities and more. Plan for lunch from a food truck!"
    }
  ]
}
